{
  "$id": "https://raw.githubusercontent.com/devicedev/cacao-json-schemas/main/schemas/workflows/action.json",
  "$schema": "http://json-schema.org/draft-07/schema#",
  "title": "action",
  "description": "The action step workflow step contains the actual commands to be executed by an agent against a set of targets. These commands are intended to be processed sequentially. In addition to the inherited properties, this section defines five more specific properties that are valid for this type.",
  "allOf": [
    {
      "$ref": "workflow-step.json"
    },
    {
      "properties": {
        "type": {
          "type": "string",
          "description": "The value of this property MUST be 'action'.",
          "enum": ["action"]
        }
      }
    }
  ],
  "unevaluatedProperties": false
}
